tcfcli/__init__.py
tcfcli/cmds/__init__.py
tcfcli/cmds/cli/__init__.py
tcfcli/cmds/cli/cli.py
tcfcli/cmds/configure/__init__.py
tcfcli/cmds/configure/cli.py
tcfcli/cmds/deploy/__init__.py
tcfcli/cmds/deploy/cli.py
tcfcli/cmds/init/__init__.py
tcfcli/cmds/init/cli.py
tcfcli/cmds/local/__init__.py
tcfcli/cmds/local/cli.py
tcfcli/cmds/local/common/__init__.py
tcfcli/cmds/local/common/invoke_context.py
tcfcli/cmds/local/common/options.py
tcfcli/cmds/local/generate_event/__init__.py
tcfcli/cmds/local/generate_event/cli.py
tcfcli/cmds/local/generate_event/events_metadata.py
tcfcli/cmds/local/generate_event/generate_event_action.py
tcfcli/cmds/local/generate_event/generate_event_service.py
tcfcli/cmds/local/generate_event/events/apigateway/proxy.js
tcfcli/cmds/local/generate_event/events/ckafka/consume.js
tcfcli/cmds/local/generate_event/events/cmq/notify.js
tcfcli/cmds/local/generate_event/events/cos/delete.js
tcfcli/cmds/local/generate_event/events/cos/post.js
tcfcli/cmds/local/generate_event/events/cos/put.js
tcfcli/cmds/local/generate_event/events/timer/timeout.js
tcfcli/cmds/local/invoke/__init__.py
tcfcli/cmds/local/invoke/cli.py
tcfcli/cmds/local/libs/__init__.py
tcfcli/cmds/local/libs/apigw/__init__.py
tcfcli/cmds/local/libs/apigw/api_service.py
tcfcli/cmds/local/libs/apigw/error_response.py
tcfcli/cmds/local/libs/apigw/local_service.py
tcfcli/cmds/local/libs/apigw/path_converter.py
tcfcli/cmds/local/libs/docker/__init__.py
tcfcli/cmds/local/libs/docker/attach_api.py
tcfcli/cmds/local/libs/docker/container.py
tcfcli/cmds/local/libs/docker/manager.py
tcfcli/cmds/local/libs/docker/utils.py
tcfcli/cmds/local/libs/events/__init__.py
tcfcli/cmds/local/libs/events/api.py
tcfcli/cmds/local/libs/local/__init__.py
tcfcli/cmds/local/libs/local/debug_context.py
tcfcli/cmds/local/libs/local/local_runtime.py
tcfcli/cmds/local/libs/local/local_runtime_manager.py
tcfcli/cmds/local/start_api/__init__.py
tcfcli/cmds/local/start_api/cli.py
tcfcli/cmds/package/__init__.py
tcf-0.1.6.dist-info/LICENSE
tcf-0.1.6.dist-info/METADATA
tcf-0.1.6.dist-info/WHEEL
tcf-0.1.6.dist-info/entry_points.txt
tcf-0.1.6.dist-info/top_level.txt
tcf-0.1.6.dist-info/RECORD
